Compiled from "Main.java"
public class Main {
  public Main();
    Code:
       0: aload_0
       1: invokespecial #1                  // Method java/lang/Object."<init>":()V
       4: return

  public static void main(java.lang.String[]);
    Code:
       0: ldc           #2                  // String Group: 535ct
       2: invokestatic  #3                  // Method InOut.Outln:(Ljava/lang/String;)V
       5: ldc           #4                  // String Student: Hodovaniuk Pavel Andreevich
       7: invokestatic  #3                  // Method InOut.Outln:(Ljava/lang/String;)V
      10: ldc           #5                  // String Variant: 5
      12: invokestatic  #3                  // Method InOut.Outln:(Ljava/lang/String;)V
      15: ldc           #6                  // String Enter text:
      17: invokestatic  #3                  // Method InOut.Outln:(Ljava/lang/String;)V
      20: invokestatic  #7                  // Method InOut.In:()Ljava/lang/String;
      23: astore_1
      24: aload_1
      25: invokestatic  #8                  // Method Outstr.printstr:(Ljava/lang/String;)V
      28: return
}
